{
  "core_identity": {
    "first_name": "Jarek",
    "last_name": "Slowinski",
    "full_name": "Jarek Slowinski",
    "email": "jarek.slowinski@ab.pl",
    "job_title": "Purchasing Director",
    "seniority": "Director"
  },
  "org_context": {
    "company_name": "AB S. A.",
    "departments": "Finance",
    "sub_departments": "Sourcing / Procurement",
    "industry": "computer hardware",
    "keywords_raw": "computer hardware manufacturing, market expansion, logistics automation, supply chain management, cloud services, ce region, sustainable development, electronics, digital transformation, other electronic parts and equipment merchant wholesalers, partner network growth, toys, logistics, business intelligence, vendor partnerships, iso 9001/14001, cee region, distributor, e-commerce, e-commerce services, market recognitions, product range, customer service, it solutions, corporate social responsibility, csr activities, it hardware, csr campaigns, b2b, software distribution, consumer electronics, market leader, sustainable business, awards and recognitions, it industry awards, supply chain, retail, e-commerce platform, global brands, product portfolio, distribution center in magnice, innovative logistics solutions, environmental management system, logistics facilities, services, household appliances, emas certification, operational efficiency, it distribution, distribution, consumer products & retail, transportation & logistics, logistics & supply chain, cloud computing, enterprise software, enterprises, computer software, information technology & services, sustainability, environmental services, renewables & environment, computer hardware, hardware, analytics, consumer internet, consumers, internet",
    "keywords_list": [
      "computer hardware manufacturing",
      "market expansion",
      "logistics automation",
      "supply chain management",
      "cloud services",
      "ce region",
      "sustainable development",
      "electronics",
      "digital transformation",
      "other electronic parts and equipment merchant wholesalers",
      "partner network growth",
      "toys",
      "logistics",
      "business intelligence",
      "vendor partnerships",
      "iso 9001/14001",
      "cee region",
      "distributor",
      "e-commerce",
      "e-commerce services",
      "market recognitions",
      "product range",
      "customer service",
      "it solutions",
      "corporate social responsibility",
      "csr activities",
      "it hardware",
      "csr campaigns",
      "b2b",
      "software distribution",
      "consumer electronics",
      "market leader",
      "sustainable business",
      "awards and recognitions",
      "it industry awards",
      "supply chain",
      "retail",
      "e-commerce platform",
      "global brands",
      "product portfolio",
      "distribution center in magnice",
      "innovative logistics solutions",
      "environmental management system",
      "logistics facilities",
      "services",
      "household appliances",
      "emas certification",
      "operational efficiency",
      "it distribution",
      "distribution",
      "consumer products & retail",
      "transportation & logistics",
      "logistics & supply chain",
      "cloud computing",
      "enterprise software",
      "enterprises",
      "computer software",
      "information technology & services",
      "sustainability",
      "environmental services",
      "renewables & environment",
      "computer hardware",
      "hardware",
      "analytics",
      "consumer internet",
      "consumers",
      "internet"
    ],
    "keywords_normalized": [
      "computer hardware manufacturing",
      "market expansion",
      "logistics automation",
      "supply chain management",
      "cloud services",
      "ce region",
      "sustainable development",
      "electronics",
      "digital transformation",
      "other electronic parts and equipment merchant wholesalers",
      "partner network growth",
      "toys",
      "logistics",
      "business intelligence",
      "vendor partnerships",
      "iso 9001/14001",
      "cee region",
      "distributor",
      "e-commerce",
      "e-commerce services",
      "market recognitions",
      "product range",
      "customer service",
      "it solutions",
      "corporate social responsibility",
      "csr activities",
      "it hardware",
      "csr campaigns",
      "b2b",
      "software distribution",
      "consumer electronics",
      "market leader",
      "sustainable business",
      "awards and recognitions",
      "it industry awards",
      "supply chain",
      "retail",
      "e-commerce platform",
      "global brands",
      "product portfolio",
      "distribution center in magnice",
      "innovative logistics solutions",
      "environmental management system",
      "logistics facilities",
      "services",
      "household appliances",
      "emas certification",
      "operational efficiency",
      "it distribution",
      "distribution",
      "consumer products & retail",
      "transportation & logistics",
      "logistics & supply chain",
      "cloud computing",
      "enterprise software",
      "enterprises",
      "computer software",
      "information technology & services",
      "sustainability",
      "environmental services",
      "renewables & environment",
      "computer hardware",
      "hardware",
      "analytics",
      "consumer internet",
      "consumers",
      "internet"
    ]
  },
  "urls": {
    "person_linkedin_url": "http://www.linkedin.com/in/jarekslowinski",
    "website": "https://ab.pl",
    "company_domain": null,
    "company_linkedin_url": "http://www.linkedin.com/company/ab-s-a-",
    "facebook_url": "https://www.facebook.com/ABInnovationDesigner",
    "twitter_url": null
  },
  "location": {
    "city": "Wroclaw",
    "state": "Lower Silesian Voivodeship",
    "country": "POLAND",
    "company_address": "2 ulica Europejska, Lower Silesian Voivodeship, Poland, 55-040",
    "company_city": null,
    "company_state": "Lower Silesian Voivodeship",
    "company_country": "POLAND"
  },
  "company_metadata": {
    "company_phone": "'+48 71 393 76 00",
    "employees_count": null,
    "annual_revenue": null,
    "company_description": null
  },
  "raw_input_metadata": {
    "original_row": {
      "First Name": "Jarek",
      "Last Name": "Slowinski",
      "Title": "Purchasing Director",
      "Company Name": "AB S. A.",
      "Email": "jarek.slowinski@ab.pl",
      "Seniority": "Director",
      "Departments": "Finance",
      "Sub Departments": "Sourcing / Procurement",
      "Industry": "computer hardware",
      "Keywords": "computer hardware manufacturing, market expansion, logistics automation, supply chain management, cloud services, ce region, sustainable development, electronics, digital transformation, other electronic parts and equipment merchant wholesalers, partner network growth, toys, logistics, business intelligence, vendor partnerships, iso 9001/14001, cee region, distributor, e-commerce, e-commerce services, market recognitions, product range, customer service, it solutions, corporate social responsibility, csr activities, it hardware, csr campaigns, b2b, software distribution, consumer electronics, market leader, sustainable business, awards and recognitions, it industry awards, supply chain, retail, e-commerce platform, global brands, product portfolio, distribution center in magnice, innovative logistics solutions, environmental management system, logistics facilities, services, household appliances, emas certification, operational efficiency, it distribution, distribution, consumer products & retail, transportation & logistics, logistics & supply chain, cloud computing, enterprise software, enterprises, computer software, information technology & services, sustainability, environmental services, renewables & environment, computer hardware, hardware, analytics, consumer internet, consumers, internet",
      "Person Linkedin Url": "http://www.linkedin.com/in/jarekslowinski",
      "Website": "https://ab.pl",
      "Company Linkedin Url": "http://www.linkedin.com/company/ab-s-a-",
      "Facebook Url": "https://www.facebook.com/ABInnovationDesigner",
      "City": "Wroclaw",
      "State": "Lower Silesian Voivodeship",
      "Country": "Poland",
      "Company Address": "2 ulica Europejska, Lower Silesian Voivodeship, Poland, 55-040",
      "Company State": "Lower Silesian Voivodeship",
      "Company Country": "Poland",
      "Company Phone": "'+48 71 393 76 00"
    },
    "unmapped_fields": {},
    "imported_at": "2026-04-21T06:56:05.032508",
    "import_history": [
      {
        "imported_at": "2026-04-21T07:02:12.832565",
        "original_row": {
          "First Name": "Jarek",
          "Last Name": "Slowinski",
          "Title": "Purchasing Director",
          "Company Name": "AB S. A.",
          "Email": "jarek.slowinski@ab.pl",
          "Seniority": "Director",
          "Departments": "Finance",
          "Sub Departments": "Sourcing / Procurement",
          "Industry": "computer hardware",
          "Keywords": "computer hardware manufacturing, market expansion, logistics automation, supply chain management, cloud services, ce region, sustainable development, electronics, digital transformation, other electronic parts and equipment merchant wholesalers, partner network growth, toys, logistics, business intelligence, vendor partnerships, iso 9001/14001, cee region, distributor, e-commerce, e-commerce services, market recognitions, product range, customer service, it solutions, corporate social responsibility, csr activities, it hardware, csr campaigns, b2b, software distribution, consumer electronics, market leader, sustainable business, awards and recognitions, it industry awards, supply chain, retail, e-commerce platform, global brands, product portfolio, distribution center in magnice, innovative logistics solutions, environmental management system, logistics facilities, services, household appliances, emas certification, operational efficiency, it distribution, distribution, consumer products & retail, transportation & logistics, logistics & supply chain, cloud computing, enterprise software, enterprises, computer software, information technology & services, sustainability, environmental services, renewables & environment, computer hardware, hardware, analytics, consumer internet, consumers, internet",
          "Person Linkedin Url": "http://www.linkedin.com/in/jarekslowinski",
          "Website": "https://ab.pl",
          "Company Linkedin Url": "http://www.linkedin.com/company/ab-s-a-",
          "Facebook Url": "https://www.facebook.com/ABInnovationDesigner",
          "City": "Wroclaw",
          "State": "Lower Silesian Voivodeship",
          "Country": "Poland",
          "Company Address": "2 ulica Europejska, Lower Silesian Voivodeship, Poland, 55-040",
          "Company State": "Lower Silesian Voivodeship",
          "Company Country": "Poland",
          "Company Phone": "'+48 71 393 76 00"
        },
        "unmapped_fields": {}
      }
    ]
  },
  "normalization_warnings": [],
  "_storage_meta": {
    "contact_key": "jarek.slowinski@ab.pl",
    "last_saved_at": "2026-04-21T07:02:12.832745"
  }
}