{
  "core_identity": {
    "first_name": "Lukasz",
    "last_name": "Stoch",
    "full_name": "Lukasz Stoch",
    "email": "stoch@teskosteel.com.pl",
    "job_title": "Strategic Procurement Director",
    "seniority": "Director"
  },
  "org_context": {
    "company_name": "Tesko Steel Sp. z o.o.",
    "departments": "Finance",
    "sub_departments": "Sourcing / Procurement",
    "industry": "mining & metals",
    "keywords_raw": "steel product, technology, park machine, production, steel trade, fabricated metal products, steel modernization, distribution, modern technologies, energy & utilities, just in time delivery, galvanized steel, services, cold-rolled steel, high-quality steel products, green transformation, steel quality assurance, energy from renewable sources, aluminum steel, ultralight trailers for transport, steel products, steel plant expansion, steel supply chain optimization, steel processing automation, transportation & logistics, steel automation, steel cutting lines, steel distribution, steel warehouse, steel product certification, rolling and drawing of purchased steel, renewable energy, steel infrastructure, advanced cutting technology, photovoltaic energy systems, it systems in steel production, hot-rolled steel, steel environmental responsibility, stainless steel, logistics, manufacturing, automation, modern infrastructure, copper steel, b2b, cutting lines, steel logistics, it solutions, energy optimization platform, logistics fleet, decarbonization, laserprec surface guarantee, steel industry innovation, steel service center, steel processing, mining & metals, clean energy & technology, environmental services, renewables & environment, mechanical or industrial engineering",
    "keywords_list": [
      "steel product",
      "technology",
      "park machine",
      "production",
      "steel trade",
      "fabricated metal products",
      "steel modernization",
      "distribution",
      "modern technologies",
      "energy & utilities",
      "just in time delivery",
      "galvanized steel",
      "services",
      "cold-rolled steel",
      "high-quality steel products",
      "green transformation",
      "steel quality assurance",
      "energy from renewable sources",
      "aluminum steel",
      "ultralight trailers for transport",
      "steel products",
      "steel plant expansion",
      "steel supply chain optimization",
      "steel processing automation",
      "transportation & logistics",
      "steel automation",
      "steel cutting lines",
      "steel distribution",
      "steel warehouse",
      "steel product certification",
      "rolling and drawing of purchased steel",
      "renewable energy",
      "steel infrastructure",
      "advanced cutting technology",
      "photovoltaic energy systems",
      "it systems in steel production",
      "hot-rolled steel",
      "steel environmental responsibility",
      "stainless steel",
      "logistics",
      "manufacturing",
      "automation",
      "modern infrastructure",
      "copper steel",
      "b2b",
      "cutting lines",
      "steel logistics",
      "it solutions",
      "energy optimization platform",
      "logistics fleet",
      "decarbonization",
      "laserprec surface guarantee",
      "steel industry innovation",
      "steel service center",
      "steel processing",
      "mining & metals",
      "clean energy & technology",
      "environmental services",
      "renewables & environment",
      "mechanical or industrial engineering"
    ],
    "keywords_normalized": [
      "steel product",
      "technology",
      "park machine",
      "production",
      "steel trade",
      "fabricated metal products",
      "steel modernization",
      "distribution",
      "modern technologies",
      "energy & utilities",
      "just in time delivery",
      "galvanized steel",
      "services",
      "cold-rolled steel",
      "high-quality steel products",
      "green transformation",
      "steel quality assurance",
      "energy from renewable sources",
      "aluminum steel",
      "ultralight trailers for transport",
      "steel products",
      "steel plant expansion",
      "steel supply chain optimization",
      "steel processing automation",
      "transportation & logistics",
      "steel automation",
      "steel cutting lines",
      "steel distribution",
      "steel warehouse",
      "steel product certification",
      "rolling and drawing of purchased steel",
      "renewable energy",
      "steel infrastructure",
      "advanced cutting technology",
      "photovoltaic energy systems",
      "it systems in steel production",
      "hot-rolled steel",
      "steel environmental responsibility",
      "stainless steel",
      "logistics",
      "manufacturing",
      "automation",
      "modern infrastructure",
      "copper steel",
      "b2b",
      "cutting lines",
      "steel logistics",
      "it solutions",
      "energy optimization platform",
      "logistics fleet",
      "decarbonization",
      "laserprec surface guarantee",
      "steel industry innovation",
      "steel service center",
      "steel processing",
      "mining & metals",
      "clean energy & technology",
      "environmental services",
      "renewables & environment",
      "mechanical or industrial engineering"
    ]
  },
  "urls": {
    "person_linkedin_url": "http://www.linkedin.com/in/%c5%82ukasz-stoch-4a0a53185",
    "website": "https://teskosteel.com.pl",
    "company_domain": null,
    "company_linkedin_url": "http://www.linkedin.com/company/tesko-steel",
    "facebook_url": null,
    "twitter_url": null
  },
  "location": {
    "city": "Krakow",
    "state": "Lesser Poland Voivodeship",
    "country": "POLAND",
    "company_address": "8a ulica Brzezinska, Silesian Voivodeship, Poland, 44-203",
    "company_city": null,
    "company_state": "Silesian Voivodeship",
    "company_country": "POLAND"
  },
  "company_metadata": {
    "company_phone": "'+48 32 432 91 31",
    "employees_count": null,
    "annual_revenue": null,
    "company_description": null
  },
  "raw_input_metadata": {
    "original_row": {
      "First Name": "Lukasz",
      "Last Name": "Stoch",
      "Title": "Strategic Procurement Director",
      "Company Name": "Tesko Steel Sp. z o.o.",
      "Email": "stoch@teskosteel.com.pl",
      "Seniority": "Director",
      "Departments": "Finance",
      "Sub Departments": "Sourcing / Procurement",
      "Industry": "mining & metals",
      "Keywords": "steel product, technology, park machine, production, steel trade, fabricated metal products, steel modernization, distribution, modern technologies, energy & utilities, just in time delivery, galvanized steel, services, cold-rolled steel, high-quality steel products, green transformation, steel quality assurance, energy from renewable sources, aluminum steel, ultralight trailers for transport, steel products, steel plant expansion, steel supply chain optimization, steel processing automation, transportation & logistics, steel automation, steel cutting lines, steel distribution, steel warehouse, steel product certification, rolling and drawing of purchased steel, renewable energy, steel infrastructure, advanced cutting technology, photovoltaic energy systems, it systems in steel production, hot-rolled steel, steel environmental responsibility, stainless steel, logistics, manufacturing, automation, modern infrastructure, copper steel, b2b, cutting lines, steel logistics, it solutions, energy optimization platform, logistics fleet, decarbonization, laserprec surface guarantee, steel industry innovation, steel service center, steel processing, mining & metals, clean energy & technology, environmental services, renewables & environment, mechanical or industrial engineering",
      "Person Linkedin Url": "http://www.linkedin.com/in/%c5%82ukasz-stoch-4a0a53185",
      "Website": "https://teskosteel.com.pl",
      "Company Linkedin Url": "http://www.linkedin.com/company/tesko-steel",
      "City": "Krakow",
      "State": "Lesser Poland Voivodeship",
      "Country": "Poland",
      "Company Address": "8a ulica Brzezinska, Silesian Voivodeship, Poland, 44-203",
      "Company State": "Silesian Voivodeship",
      "Company Country": "Poland",
      "Company Phone": "'+48 32 432 91 31"
    },
    "unmapped_fields": {},
    "imported_at": "2026-04-21T06:56:05.047038",
    "import_history": [
      {
        "imported_at": "2026-04-21T07:02:12.858368",
        "original_row": {
          "First Name": "Lukasz",
          "Last Name": "Stoch",
          "Title": "Strategic Procurement Director",
          "Company Name": "Tesko Steel Sp. z o.o.",
          "Email": "stoch@teskosteel.com.pl",
          "Seniority": "Director",
          "Departments": "Finance",
          "Sub Departments": "Sourcing / Procurement",
          "Industry": "mining & metals",
          "Keywords": "steel product, technology, park machine, production, steel trade, fabricated metal products, steel modernization, distribution, modern technologies, energy & utilities, just in time delivery, galvanized steel, services, cold-rolled steel, high-quality steel products, green transformation, steel quality assurance, energy from renewable sources, aluminum steel, ultralight trailers for transport, steel products, steel plant expansion, steel supply chain optimization, steel processing automation, transportation & logistics, steel automation, steel cutting lines, steel distribution, steel warehouse, steel product certification, rolling and drawing of purchased steel, renewable energy, steel infrastructure, advanced cutting technology, photovoltaic energy systems, it systems in steel production, hot-rolled steel, steel environmental responsibility, stainless steel, logistics, manufacturing, automation, modern infrastructure, copper steel, b2b, cutting lines, steel logistics, it solutions, energy optimization platform, logistics fleet, decarbonization, laserprec surface guarantee, steel industry innovation, steel service center, steel processing, mining & metals, clean energy & technology, environmental services, renewables & environment, mechanical or industrial engineering",
          "Person Linkedin Url": "http://www.linkedin.com/in/%c5%82ukasz-stoch-4a0a53185",
          "Website": "https://teskosteel.com.pl",
          "Company Linkedin Url": "http://www.linkedin.com/company/tesko-steel",
          "City": "Krakow",
          "State": "Lesser Poland Voivodeship",
          "Country": "Poland",
          "Company Address": "8a ulica Brzezinska, Silesian Voivodeship, Poland, 44-203",
          "Company State": "Silesian Voivodeship",
          "Company Country": "Poland",
          "Company Phone": "'+48 32 432 91 31"
        },
        "unmapped_fields": {}
      }
    ]
  },
  "normalization_warnings": [],
  "_storage_meta": {
    "contact_key": "stoch@teskosteel.com.pl",
    "last_saved_at": "2026-04-21T07:02:12.858692"
  }
}